kotanipay_sdk/__init__.py
kotanipay_sdk/config.py
kotanipay_sdk/kotanipay.py
kotanipay_sdk/models.py
kotanipay_sdk/customer/__init__.py
kotanipay_sdk/customer/customer.py
kotanipay_sdk/customer/customerModels.py
kotanipay_sdk/transact/__init__.py
kotanipay_sdk/transact/transact.py
kotanipay_sdk/transact/transactModels.py
kotanipay_sdk/wallet/__init__.py
kotanipay_sdk/wallet/wallet.py
kotanipay_sdk/wallet/walletModels.py
kotanipay-0.0.1.dist-info/METADATA
kotanipay-0.0.1.dist-info/WHEEL
kotanipay-0.0.1.dist-info/top_level.txt
kotanipay-0.0.1.dist-info/RECORD
