Metadata-Version: 2.1
Name: kotanipay
Version: 0.0.1
Summary: KotaniPay Unofficial Python Packaga
Home-page: UNKNOWN
Author: David Marko
Author-email: markodave46@gmail.com
License: UNKNOWN
Keywords: python,kotanipay,mpesa,crypto
Platform: UNKNOWN
Requires-Dist: requests
Requires-Dist: pydantic
Requires-Dist: pydantic[email]
